arconfig.py
arconfig-0.1.3.dist-info/METADATA
arconfig-0.1.3.dist-info/RECORD
arconfig-0.1.3.dist-info/WHEEL
arconfig-0.1.3.dist-info/top_level.txt
