Metadata-Version: 2.1
Name: arconfig
Version: 0.1.3
Summary: Load and gen configuration for argparse
Home-page: http://github.com/mosquito/arconfig
Author: Dmitry Orlov <me@mosquito.su>
Author-email: me@mosquito.su
License: MIT
Platform: all
Classifier: Environment :: Console
Classifier: Programming Language :: Python
